raspy_auto/__init__.py
raspy_auto/api/__init__.py
raspy_auto/api/api.py
raspy_auto/api/running.py
raspy_auto/ras/__init__.py
raspy_auto/ras/ras.py
raspy_auto/ras/wrapper.py
raspy_auto-1.1.1.dist-info/METADATA
raspy_auto-1.1.1.dist-info/WHEEL
raspy_auto-1.1.1.dist-info/top_level.txt
raspy_auto-1.1.1.dist-info/RECORD
