Metadata-Version: 2.1
Name: raspy_auto
Version: 1.1.1
Summary: A HEC-RAS automation library
Home-page: https://github.com/quantum-dan/raspy
Author: Daniel Philippus
Author-email: daniel@dphilippus.com
Project-URL: Bug Tracker, https://github.com/quantum-dan/raspy/issues
Classifier: Programming Language :: Python :: 3
Classifier: License :: OSI Approved :: GNU General Public License v3 (GPLv3)
Classifier: Operating System :: Microsoft :: Windows
Requires-Python: >=3.6
Requires-Dist: pyrasfile
Requires-Dist: pywin32
